README.md
setup.cfg
setup.py
Dvina.egg-info/PKG-INFO
Dvina.egg-info/SOURCES.txt
Dvina.egg-info/dependency_links.txt
Dvina.egg-info/requires.txt
Dvina.egg-info/top_level.txt
dvina/__init__.py
dvina/_example.py
dvina/_example_batch_pool.py
dvina/_meta_model.py
dvina/_ranked_example_pool.py
dvina/_ranked_pool_sampler.py
dvina/_ranked_pool_standard.py
dvina/_ranking_worker.py
dvina/active_labeler.py
dvina/basic_data_processor.py
dvina/csv_data_provider.py
dvina/data_processor.py
dvina/logger_configurator.py
dvina/_models/__init__.py
dvina/_models/_offline_evaluator.py
dvina/_models/_qbc_sampler.py
dvina/_models/_random_sampler.py
dvina/_models/_standard_evaluator.py
dvina/_models/_uncertainty_sampler.py
dvina/_models/base.py
dvina/_models/sklearn_classifier.py
dvina/_utils/__init__.py
dvina/_utils/classes.py
dvina/_utils/iter.py
dvina/_utils/serialization.py
dvina/_utils/utils.py