Metadata-Version: 1.0
Name: Dvina
Version: 1.0
Summary: Dvina Active Labeling library
Home-page: UNKNOWN
Author: UNKNOWN
Author-email: UNKNOWN
License: UNKNOWN
Platform: UNKNOWN
